{
  "posts": [
    {
      "firstname": "jhbihvy",
      "lastname": "uyvuv",
      "birthdate": "275760-06-05",
      "gender": "m",
      "education": "12th Pass",
      "company": "jhuh",
      "jobExperience": 656854,
      "salary": 54956,
      "id": 1
    },
    {
      "firstname": "hgvugc",
      "lastname": "utgfu8gf",
      "birthdate": "275760-05-06",
      "gender": "m",
      "education": "12th Pass",
      "company": "jhgvuyyi",
      "jobExperience": 649864,
      "salary": 8964964,
      "profile": "WIN_20230118_18_22_14_Pro.jpg",
      "id": 2
    }
  ],
  "comments": [],
  "profile": {
    "name": "typicode"
  }
}